tensorflow_text/__init__.py
tensorflow_text/core/pybinds/pywrap_fast_bert_normalizer_model_builder.so
tensorflow_text/core/pybinds/pywrap_fast_wordpiece_tokenizer_model_builder.so
tensorflow_text/core/pybinds/pywrap_model_converter.so
tensorflow_text/core/pybinds/pywrap_phrase_tokenizer_model_builder.so
tensorflow_text/core/pybinds/pywrap_whitespace_tokenizer_config_builder.so
tensorflow_text/core/pybinds/tflite_registrar.so
tensorflow_text/python/__init__.py
tensorflow_text/python/keras/__init__.py
tensorflow_text/python/keras/layers/__init__.py
tensorflow_text/python/keras/layers/todense.py
tensorflow_text/python/keras/layers/tokenization_layers.py
tensorflow_text/python/metrics/__init__.py
tensorflow_text/python/metrics/_text_similarity_metric_ops.dylib
tensorflow_text/python/metrics/text_similarity_metric_ops.py
tensorflow_text/python/numpy/__init__.py
tensorflow_text/python/numpy/viterbi_decode.py
tensorflow_text/python/ops/__init__.py
tensorflow_text/python/ops/_boise_offset_converter.dylib
tensorflow_text/python/ops/_byte_splitter.dylib
tensorflow_text/python/ops/_constrained_sequence_op.dylib
tensorflow_text/python/ops/_fast_bert_normalizer.dylib
tensorflow_text/python/ops/_fast_sentencepiece_tokenizer.dylib
tensorflow_text/python/ops/_fast_wordpiece_tokenizer.dylib
tensorflow_text/python/ops/_mst_ops.dylib
tensorflow_text/python/ops/_ngrams_op.dylib
tensorflow_text/python/ops/_normalize_ops.dylib
tensorflow_text/python/ops/_phrase_tokenizer.dylib
tensorflow_text/python/ops/_regex_split_ops.dylib
tensorflow_text/python/ops/_sentence_breaking_ops.dylib
tensorflow_text/python/ops/_sentencepiece_tokenizer.dylib
tensorflow_text/python/ops/_split_merge_from_logits_tokenizer.dylib
tensorflow_text/python/ops/_split_merge_tokenizer.dylib
tensorflow_text/python/ops/_state_based_sentence_breaker_op.dylib
tensorflow_text/python/ops/_trimmer_ops.dylib
tensorflow_text/python/ops/_unicode_script_tokenizer.dylib
tensorflow_text/python/ops/_utf8_binarize_op.dylib
tensorflow_text-2.19.0.dist-info/LICENSE
tensorflow_text-2.19.0.dist-info/METADATA
tensorflow_text-2.19.0.dist-info/WHEEL
tensorflow_text-2.19.0.dist-info/top_level.txt
tensorflow_text-2.19.0.dist-info/RECORD
